Metadata-Version: 1.1
Name: tweaked-graphviz
Version: 0.0.6
Summary: A tweaked version of an interactive graphviz viewer for Dash
Home-page: https://github.com/PhilipPeters/tweaked_graphviz
Author: Philip Peters
Author-email: pcpworld@yahoo.co.uk
License: MIT
Download-URL: https://github.com/PhilipPeters/tweaked_graphviz/archive/0.0.6.tar.gz
Keywords: React,Dash,Graphviz
Platform: UNKNOWN
Classifier: Development Status :: 3 - Alpha
Classifier: Intended Audience :: Developers
Classifier: Topic :: Software Development :: Build Tools
Classifier: License :: OSI Approved :: MIT License
Classifier: Programming Language :: Python :: 3
Classifier: Programming Language :: Python :: 3.4
Classifier: Programming Language :: Python :: 3.5
Classifier: Programming Language :: Python :: 3.6
Classifier: Programming Language :: Python :: 3.7
Classifier: Programming Language :: Python :: 3.8
Classifier: Programming Language :: Python :: 3.9
